[
{
"messageID":"123456789",
"recipient":"+27019090909",
"status":"Stored",
"message":"are you still there"
},
{
"messageID":"987654321",
"recipient":"+27908765431",
"status":"Stored",
"message":"did you recieve my message"
},
{
"messageID":"123456789",
"recipient":"+27019090909",
"status":"Stored",
"message":"are you still there"
},
{
"messageID":"987654321",
"recipient":"+27908765431",
"status":"Stored",
"message":"did you recieve my message"
},
{
"messageID":"123234345",
"recipient":"+27123456789",
"status":"Stored",
"message":"due date tomorrow"
}
]